[
  {
    "Title": "Kickoff-webinar",
    "Subtitle": "Schrijf je nu in voor de kickoff-webinar van a.s. donderdag en ontdek alle nieuwe functies!",
    "ButtonText": "Schrijf je in",
    "ButtonLink": "https://unlit.webinargeek.com/channel/unlit-studio-webinars",
    "ImageURL": "https://UnlitStudio.github.io/Public/Data/Homepage/Update_Showcase.jpg"
  },
  {
    "Title": "Unlit is gelanceerd!",
    "Subtitle": "Onze lancering in de tuinenbranche is een feit. Schrijf je in voor de nieuwsbrief en blijf altijd op de hoogte.",
    "ButtonText": "Aanmelden",
    "ButtonLink": "https://5aabz.share.hsforms.com/2BpCcotwwTGSGKNOrEYyShw",
    "ImageURL": "https://UnlitStudio.github.io/Public/Data/Homepage/Render_Unlit_Tuinen.jpg"
  },
  {
    "Title": "Demo & Masterclasses",
    "Subtitle": "Leer in gratis webinars/masterclasses de kracht van Unlit Studio kennen.",
    "ButtonText": "Bekijk de webinars",
    "ButtonLink": "https://www.unlit.studio/webinar",
    "ImageURL": "https://UnlitStudio.github.io/Public/Data/Homepage/Homepage_BreesNewWorld.jpg"
  },
  {
    "Title": "Live Training in Zwolle & Boxtel",
    "Subtitle": "Hands-on training met een professional om Unlit Studio optimaal te leren gebruiken.",
    "ButtonText": "Schrijf je in",
    "ButtonLink": "https://www.unlit.studio/training",
    "ImageURL": "https://UnlitStudio.github.io/Public/Data/Homepage/Mockup_Unlit_Studio.jpg"
  }
]
